.travis.yml
licence
readme.md
requirements-dev.txt
requirements.txt
setup.cfg
setup.py
tox.ini
data_pipe.egg-info/PKG-INFO
data_pipe.egg-info/SOURCES.txt
data_pipe.egg-info/dependency_links.txt
data_pipe.egg-info/entry_points.txt
data_pipe.egg-info/not-zip-safe
data_pipe.egg-info/pbr.json
data_pipe.egg-info/requires.txt
data_pipe.egg-info/top_level.txt
src/readme.md
src/main/readme.md
src/main/data_pipe/.gitignore
src/main/data_pipe/__init__.py
src/main/data_pipe/any_buffer.py
src/main/data_pipe/any_index.py
src/main/data_pipe/basic_buffer.py
src/main/data_pipe/basic_index.py
src/main/data_pipe/basic_ruptor.py
src/main/data_pipe/basic_trunk.py
src/main/data_pipe/native_any.h
src/main/data_pipe/native_any.pxd
src/main/data_pipe/native_buffer.py
src/main/data_pipe/native_buffer.pyx
src/main/data_pipe/native_index.pyx
src/main/data_pipe/native_ruptor.pyx
src/main/data_pipe/runtime_library.pyx
src/perf/readme.md
src/perf/data_pipe_perf/__init__.py
src/perf/data_pipe_perf/any_buffer_perf.py
src/perf/data_pipe_perf/any_ruptor_perf.py
src/perf/data_pipe_perf/basic_buffer_perf.py
src/perf/data_pipe_perf/native_buffer_perf.py
src/perf/data_pipe_perf/py_asio_queue_perf.py
src/perf/data_pipe_perf/py_curio_queue_perf.py
src/perf/data_pipe_perf/py_os_pipe_perf.py
src/perf/data_pipe_perf/py_sync_queue_perf.py
src/perf/data_pipe_perf/py_trio_queue_perf.py
src/test/readme.md
src/test/data_pipe_test/__init__.py
src/test/data_pipe_test/any_buffer_test.py
src/test/data_pipe_test/basic_buffer_test.py
src/test/data_pipe_test/basic_index_test.py
src/test/data_pipe_test/basic_ruptor_test.py
src/test/data_pipe_test/basic_trunk_test.py
src/test/data_pipe_test/native_buffer_test.py
src/test/data_pipe_test/native_futex_test.py
src/test/data_pipe_test/native_index_test.py
src/test/data_pipe_test/native_ruptor_test.py
src/test/data_pipe_test/verify_buffer.py
src/test/data_pipe_test/verify_index.py
src/verify/readme.md
src/verify/design/__init__.py
src/verify/design/buffer.py
src/verify/design/buffer_test.py
src/verify/design/channel.py
src/verify/design/message.py
src/verify/design/native.py
src/verify/design/native_a.h
src/verify/design/native_a1.h
src/verify/design/native_base_test.py
src/verify/design/native_code.c
