Metadata-Version: 2.1
Name: data-pipe
Version: 0.2.2.dev6
Summary: Cross Thread Message Pipe
Home-page: https://github.com/random-python/data_pipe
Author: Andrei Pozolotin
Author-email: andrei.pozolotin@gmail.com
License: Apache-2
Keywords: cross,thread,process,message,pipe,memory,channel,trio,curio,asyncio,threading,multiprocessing
Platform: UNKNOWN
Classifier: Development Status :: 4 - Beta
Classifier: Intended Audience :: Developers
Classifier: License :: OSI Approved :: Apache Software License
Classifier: Operating System :: POSIX :: Linux
Classifier: Programming Language :: Python
Classifier: Programming Language :: Python :: 3.8
Classifier: Topic :: Utilities
